{
  "date": "2026-04-23",
  "social_updates": "📭 今日暫無最新動態",
  "books_and_works": "微信讀書平台顯示蔡康永著作今日閱讀熱度更新：《因為這是你的人生》有153人閱讀,《蔡康永的說話之道》有150人閱讀,《為你自己活一次（獨家首發）》有43人閱讀,《蔡康永的說話之道2（獨家首發）》有24人閱讀,《蔡康永的說話之道（全2冊）》有17人閱讀,《蔡康永的情商課（全2冊）》有16人閱讀,微信讀書平台介紹《因為這是你的人生》強調26招拿捏社交、馬東認證600萬讀者有效、融合認知心理學與東方文化，並收錄瓜幾拉貓咪插畫與康永哥人際關係心法,微信讀書平台介紹《為你自己活一次（獨家首發）》為情商之神蔡康永的「內心強大之道」，開啟中國式情商課程先河，透過認知心理學拆解職場、情場、社交難題，含30+真實案例，旨在不委屈自己也不為難別人,微信讀書平台介紹《蔡康永的說話之道2（獨家首發）》為熱銷500萬冊國民經典，蔡康永2020年親自修訂加入全新8章，由酚酞瓜執筆88幅四格漫畫，強調「對你好」的說話之道，讓談話有趣、人際相處更融洽,微信讀書平台介紹《蔡康永的說話之道（全2冊）》為蔡康永詮釋「說話的藝術」隨筆集，透過研究「說話」幫助讀者明確人際關係與思維邏輯，提升自我理解與生活幸福感,圓神書活網深入解析《蔡康永的情商課2：因為這是你的人生》書中精華，收錄蔡康永對「怎麼交朋友」的見解，包括「交朋友跟買東西不一樣」、「抱怨朋友現實是因自己用現實標準衡量友誼」、「活著沒有標準範本，只有適合我們的劇本」、「當拍照時補光的反光板讓朋友變有趣」、「想增加自信或鬥志可與他人比較強弱處」、「令你自在的是友誼，焦慮的是人脈」,圓神書活網深入解析《蔡康永的情商課2：因為這是你的人生》書中精華，收錄蔡康永對「怎麼同時滿足爸媽又成就自己」的見解，包括「若覺得虧欠對方就會被勒索」、「若受不了不了解或不愛自己的爸媽可在心裡幻想一對理想父母」、「區分父母期望與自己的願望並衡量心力做分配」、「小事滿足父母期望以儲備談判籌碼，希望大事能尊重自己意願」,迷誠品發表全新書評《讀蔡康永新書《你願意，人生就會值得》：唯有經歷過，才能感受個中滋味》，聚焦《蔡康永的情商課3：《你願意，人生就會值得》》",
  "hosting_programs": "📭 今日暫無最新動態",
  "related_news": "📭 今日暫無最新動態",
  "score": 80,
  "source_data_count": 10
}