{
  "date": "2026-03-30",
  "social_updates": [
    "香港讀書帳號@hk.little.booker在Instagram分享《蔡康永的情商課1》讀後感，並歸納出金句：「為自己而活，做自己情緒的主人」、「改變不一定是壞，失去才能成長」、「旁觀者清，不一定要當主角」。",
    "網友@_reading_lab_在Threads分享讀《蔡康永的說話之道》心得，特別引用金句：「語言最美的時候，就是我們透過語言、感受到彼此互相需要的時候。」強調溝通的本質是連結而非自我表達。",
    "VOGUE Taiwan 於3月1日發文祝蔡康永64歲生日快樂，並引用其金句：「在日常生活中能夠感受自己活著，比標榜夢想跟追逐夢想的能力重要太多了。」"
  ],
  "books_and_works": [
    "誠品書店Threads帳號推薦「蔡康永情商課系列」，特別提及《別再騙自己》以明快的金句和解釋結構易讀，《永遠記得》則以短句和大量插圖觸動人心，持續分享其情商課的魅力。",
    "博客來網站上架《你願意，人生就會值得：蔡康永的情商課3》，作為其情商課系列的最新作品之一，持續探討人生價值觀。",
    "YouTube上出現由「文月」整理的《蔡康永的說話之道》全41集有聲書播放清單，提供多媒體形式的閱讀體驗。",
    "部落格文章《Book Review: Kevin Tsai's Way Of Speaking (蔡康永的说话之道)》發布，評論了《蔡康永的說話之道》第一部和第二部，並提及書中關於自信表達的觀點，如「我就是同志。那又如何？」",
    "微信讀書平台持續推薦蔡康永多部作品，包括《蔡康永手把手教你人际关系之道》、《蔡康永的高情商话术》新升級版及獨家首發的《为你自己活一次》，顯示其著作受讀者廣泛歡迎。"
  ],
  "hosting_programs": [
    "YouTube頻道持續發布《康熙來了》的精彩片段，例如「【#ㄎㄧㄤ精彩 1974】穿著Prada的惡魔S.Ver 怎麼敢穿這樣上節目啊?! |EP4|」，顯示節目內容持續被重溫與分享。",
    "YouTube上持續有《康熙來了》的播放清單更新與維護，顯示觀眾仍能回顧他過去的主持作品。",
    "《康熙來了》Facebook 官方頁面於近期持續分享節目片段，其中一個關於「蔡康永的說話之道」的影片，即便發佈於2025年12月，仍在2026年3月獲得大量觀看與討論，顯示節目舊內容仍具影響力。"
  ],
  "related_news": [
    "Dcard閒聊板出現熱議話題「康熙終於要合體了！？」，顯示大眾對蔡康永與小S再度合作主持節目的期待與關注。"
  ],
  "score": 80,
  "source_data_count": 34
}